aliyunsdkresourcemanager/__init__.py
aliyunsdkresourcemanager/endpoint.py
aliyunsdkresourcemanager/request/__init__.py
aliyunsdkresourcemanager/request/v20200331/AcceptHandshakeRequest.py
aliyunsdkresourcemanager/request/v20200331/AttachControlPolicyRequest.py
aliyunsdkresourcemanager/request/v20200331/AttachPolicyRequest.py
aliyunsdkresourcemanager/request/v20200331/BindSecureMobilePhoneRequest.py
aliyunsdkresourcemanager/request/v20200331/CancelChangeAccountEmailRequest.py
aliyunsdkresourcemanager/request/v20200331/CancelCreateCloudAccountRequest.py
aliyunsdkresourcemanager/request/v20200331/CancelHandshakeRequest.py
aliyunsdkresourcemanager/request/v20200331/CancelPromoteResourceAccountRequest.py
aliyunsdkresourcemanager/request/v20200331/ChangeAccountEmailRequest.py
aliyunsdkresourcemanager/request/v20200331/CheckAccountDeleteRequest.py
aliyunsdkresourcemanager/request/v20200331/CreateAutoGroupingRuleRequest.py
aliyunsdkresourcemanager/request/v20200331/CreateCloudAccountRequest.py
aliyunsdkresourcemanager/request/v20200331/CreateControlPolicyRequest.py
aliyunsdkresourcemanager/request/v20200331/CreateFolderRequest.py
aliyunsdkresourcemanager/request/v20200331/CreatePolicyRequest.py
aliyunsdkresourcemanager/request/v20200331/CreatePolicyVersionRequest.py
aliyunsdkresourcemanager/request/v20200331/CreateResourceAccountRequest.py
aliyunsdkresourcemanager/request/v20200331/CreateResourceGroupRequest.py
aliyunsdkresourcemanager/request/v20200331/CreateRoleRequest.py
aliyunsdkresourcemanager/request/v20200331/CreateServiceLinkedRoleRequest.py
aliyunsdkresourcemanager/request/v20200331/DeclineHandshakeRequest.py
aliyunsdkresourcemanager/request/v20200331/DeleteAccountRequest.py
aliyunsdkresourcemanager/request/v20200331/DeleteAutoGroupingRuleRequest.py
aliyunsdkresourcemanager/request/v20200331/DeleteControlPolicyRequest.py
aliyunsdkresourcemanager/request/v20200331/DeleteFolderRequest.py
aliyunsdkresourcemanager/request/v20200331/DeletePolicyRequest.py
aliyun_python_sdk_resourcemanager-1.2.7.dist-info/LICENSE
aliyun_python_sdk_resourcemanager-1.2.7.dist-info/METADATA
aliyun_python_sdk_resourcemanager-1.2.7.dist-info/WHEEL
aliyun_python_sdk_resourcemanager-1.2.7.dist-info/top_level.txt
aliyun_python_sdk_resourcemanager-1.2.7.dist-info/RECORD
